03_memory_based_dv/tb/output_checker.sv
`timescale 1ns/1ps

// -----------------------------------------------------------------------------
// File-based Output Checker
//   1) Parses output.txt reference data and valid sections.
//   2) Compares DUT oData/oDataEn on every checked clock.
//   3) Counts valid output samples and checks the final count.
// -----------------------------------------------------------------------------
module output_checker #(
    parameter integer DATA_WIDTH  = 16,
    parameter integer MAX_VECTORS = 2048
) (
    input  logic                  iClk,
    input  logic                  iRsn,
    input  logic                  oDataEn,
    input  logic [DATA_WIDTH-1:0] oData,
    output logic                  checker_done,
    output integer                error_count,
    output integer                compared_sample_count,
    output integer                actual_valid_count
);

    logic [DATA_WIDTH-1:0] expected_data  [0:MAX_VECTORS-1];
    logic                  expected_valid [0:MAX_VECTORS-1];

    integer expected_data_count;
    integer expected_valid_vector_count;
    integer expected_valid_count;

    integer scenario_id;
    string  output_filename;
    string  log_filename;

    task automatic parse_output_file(input string filename);
        integer fd;
        integer status;
        integer section_id;
        integer parsed_number;
        string  line;
        string  data_type;
        string  stage_name;
        begin
            expected_data_count         = 0;
            expected_valid_vector_count = 0;
            expected_valid_count        = 0;
            section_id                  = 0;

            fd = $fopen(filename, "r");
            if (fd == 0)
                $fatal(1, "[CHECKER] Cannot open %s", filename);

            while (!$feof(fd)) begin
                line   = "";
                status = $fgets(line, fd);

                if ($sscanf(line, "tag: data_type=%s stage=%s", data_type, stage_name) == 2) begin
                    if (data_type == "data")
                        section_id = 1;
                    else if (data_type == "valid")
                        section_id = 2;
                    else
                        section_id = 0;
                end
                else if ($sscanf(line, "%d", parsed_number) == 1) begin
                    if (section_id == 1) begin
                        if (expected_data_count >= MAX_VECTORS)
                            $fatal(1, "[CHECKER] Expected data overflow");
                        expected_data[expected_data_count] = parsed_number[DATA_WIDTH-1:0];
                        expected_data_count = expected_data_count + 1;
                    end
                    else if (section_id == 2) begin
                        if (expected_valid_vector_count >= MAX_VECTORS)
                            $fatal(1, "[CHECKER] Expected valid overflow");
                        expected_valid[expected_valid_vector_count] = (parsed_number != 0);
                        if (parsed_number != 0)
                            expected_valid_count = expected_valid_count + 1;
                        expected_valid_vector_count = expected_valid_vector_count + 1;
                    end
                end
            end

            $fclose(fd);

            if (expected_data_count == 0)
                $fatal(1, "[CHECKER] No reference values in %s", filename);

            if (expected_valid_vector_count != expected_data_count)
                $fatal(1,
                    "[CHECKER] output.txt data/valid count mismatch: data=%0d valid=%0d",
                    expected_data_count, expected_valid_vector_count);

            $display("[CHECKER] Loaded %0d reference cycles, valid outputs=%0d",
                     expected_data_count, expected_valid_count);
        end
    endtask

    initial begin : CHECKER_MAIN
        integer sample_index;
        integer log_fd;

        checker_done         = 1'b0;
        error_count          = 0;
        compared_sample_count = 0;
        actual_valid_count   = 0;

        if (!$value$plusargs("SCENARIO=%d", scenario_id))
            scenario_id = 2;

        output_filename = $sformatf("vectors/scenario%0d/output.txt", scenario_id);
        log_filename    = $sformatf("results/scenario%0d_simulation.log", scenario_id);

        parse_output_file(output_filename);

        log_fd = $fopen(log_filename, "w");
        if (log_fd != 0) begin
            $fdisplay(log_fd, "Project 3 memory delay logic checker");
            $fdisplay(log_fd, "Scenario: %0d", scenario_id);
            $fdisplay(log_fd, "Reference cycles: %0d", expected_data_count);
        end

        // The first output.txt value corresponds to the first rising edge after
        // active-low reset is released by the Input Driver.
        wait (iRsn === 1'b1);

        for (sample_index = 0;
             sample_index < expected_data_count;
             sample_index = sample_index + 1) begin
            @(posedge iClk);
            #1;

            compared_sample_count = compared_sample_count + 1;

            if (oDataEn)
                actual_valid_count = actual_valid_count + 1;

            if (oData !== expected_data[sample_index]) begin
                error_count = error_count + 1;
                $display("[CHECKER][DATA ERROR] sample=%0d expected=%0d actual=%0d",
                         sample_index + 1, expected_data[sample_index], oData);
                if (log_fd != 0)
                    $fdisplay(log_fd,
                        "DATA ERROR sample=%0d expected=%0d actual=%0d",
                        sample_index + 1, expected_data[sample_index], oData);
            end

            if (oDataEn !== expected_valid[sample_index]) begin
                error_count = error_count + 1;
                $display("[CHECKER][VALID ERROR] sample=%0d expected=%0b actual=%0b",
                         sample_index + 1, expected_valid[sample_index], oDataEn);
                if (log_fd != 0)
                    $fdisplay(log_fd,
                        "VALID ERROR sample=%0d expected=%0b actual=%0b",
                        sample_index + 1, expected_valid[sample_index], oDataEn);
            end
        end

        // Explicit output-count check required by the assignment.
        if (actual_valid_count != expected_valid_count) begin
            error_count = error_count + 1;
            $display("[CHECKER][COUNT ERROR] expected valid outputs=%0d actual=%0d",
                     expected_valid_count, actual_valid_count);
            if (log_fd != 0)
                $fdisplay(log_fd,
                    "COUNT ERROR expected=%0d actual=%0d",
                    expected_valid_count, actual_valid_count);
        end

        if (compared_sample_count != expected_data_count) begin
            error_count = error_count + 1;
            $display("[CHECKER][SAMPLE COUNT ERROR] expected=%0d actual=%0d",
                     expected_data_count, compared_sample_count);
        end

        if (error_count == 0) begin
            $display("[CHECKER][PASS] Scenario %0d: %0d cycles, %0d valid outputs",
                     scenario_id, compared_sample_count, actual_valid_count);
            if (log_fd != 0)
                $fdisplay(log_fd,
                    "PASS cycles=%0d valid_outputs=%0d errors=0",
                    compared_sample_count, actual_valid_count);
        end
        else begin
            $display("[CHECKER][FAIL] Scenario %0d: errors=%0d",
                     scenario_id, error_count);
            if (log_fd != 0)
                $fdisplay(log_fd, "FAIL errors=%0d", error_count);
        end

        if (log_fd != 0)
            $fclose(log_fd);

        checker_done = 1'b1;
    end

endmodule

03_memory_based_dv/tb/input_driver.sv
`timescale 1ns/1ps

// -----------------------------------------------------------------------------
// File-based Input Driver
//   1) Parses Input.txt and separates data/valid sections by data_type tag.
//   2) Parses register.txt and applies the initial Delay plus optional DelayAt
//      events used by the delay-change scenario.
//   3) Drives one vector per clock while preserving invalid time slots.
// -----------------------------------------------------------------------------
module input_driver #(
    parameter integer DATA_WIDTH       = 16,
    parameter integer DEPTH            = 10,
    parameter integer DELAY_WIDTH      = (DEPTH <= 1) ? 1 : $clog2(DEPTH + 1),
    parameter integer MAX_VECTORS      = 1024,
    parameter integer MAX_DELAY_EVENTS = 32
) (
    input  logic                   iClk,
    output logic                   iRsn,
    output logic                   iDataEn,
    output logic [DATA_WIDTH-1:0]  iData,
    output logic [DELAY_WIDTH-1:0] iDelay,
    output logic                   driver_done,
    output integer                 driven_cycle_count
);

    logic [DATA_WIDTH-1:0] data_vector  [0:MAX_VECTORS-1];
    logic                  valid_vector [0:MAX_VECTORS-1];

    integer data_count;
    integer valid_count;

    integer delay_event_cycle [0:MAX_DELAY_EVENTS-1];
    logic [DELAY_WIDTH-1:0] delay_event_value [0:MAX_DELAY_EVENTS-1];
    integer delay_event_count;
    logic [DELAY_WIDTH-1:0] initial_delay;

    integer scenario_id;
    string  input_filename;
    string  register_filename;

    task automatic parse_input_file(input string filename);
        integer fd;
        integer status;
        integer section_id;
        integer parsed_number;
        string  line;
        string  data_type;
        string  stage_name;
        begin
            data_count  = 0;
            valid_count = 0;
            section_id  = 0;

            fd = $fopen(filename, "r");
            if (fd == 0)
                $fatal(1, "[INPUT DRIVER] Cannot open %s", filename);

            while (!$feof(fd)) begin
                line   = "";
                status = $fgets(line, fd);

                if ($sscanf(line, "tag: data_type=%s stage=%s", data_type, stage_name) == 2) begin
                    if (data_type == "data")
                        section_id = 1;
                    else if (data_type == "valid")
                        section_id = 2;
                    else
                        section_id = 0;
                end
                else if ($sscanf(line, "%d", parsed_number) == 1) begin
                    if (section_id == 1) begin
                        if (data_count >= MAX_VECTORS)
                            $fatal(1, "[INPUT DRIVER] Data vector overflow");
                        data_vector[data_count] = parsed_number[DATA_WIDTH-1:0];
                        data_count = data_count + 1;
                    end
                    else if (section_id == 2) begin
                        if (valid_count >= MAX_VECTORS)
                            $fatal(1, "[INPUT DRIVER] Valid vector overflow");
                        valid_vector[valid_count] = (parsed_number != 0);
                        valid_count = valid_count + 1;
                    end
                end
            end

            $fclose(fd);

            if (data_count == 0)
                $fatal(1, "[INPUT DRIVER] No data vectors in %s", filename);

            if (data_count != valid_count)
                $fatal(1,
                    "[INPUT DRIVER] Data/valid count mismatch: data=%0d valid=%0d",
                    data_count, valid_count);

            $display("[INPUT DRIVER] Loaded %0d input cycles from %s",
                     data_count, filename);
        end
    endtask

    task automatic parse_register_file(input string filename);
        integer fd;
        integer status;
        integer parsed_cycle;
        logic [31:0] parsed_word;
        string line;
        begin
            initial_delay    = 1;
            delay_event_count = 0;

            fd = $fopen(filename, "r");
            if (fd == 0)
                $fatal(1, "[INPUT DRIVER] Cannot open %s", filename);

            while (!$feof(fd)) begin
                line   = "";
                status = $fgets(line, fd);

                // Optional extension for scenario 3:
                // DelayAt <1-based input cycle> <hex delay value>
                if ($sscanf(line, "DelayAt %d %h", parsed_cycle, parsed_word) == 2) begin
                    if (delay_event_count >= MAX_DELAY_EVENTS)
                        $fatal(1, "[INPUT DRIVER] Delay event overflow");

                    delay_event_cycle[delay_event_count] = parsed_cycle;
                    delay_event_value[delay_event_count] = parsed_word[DELAY_WIDTH-1:0];
                    delay_event_count = delay_event_count + 1;
                end
                else if ($sscanf(line, "Delay %h", parsed_word) == 1) begin
                    initial_delay = parsed_word[DELAY_WIDTH-1:0];
                end
            end

            $fclose(fd);

            if ((initial_delay < 1) || (initial_delay > DEPTH))
                $fatal(1, "[INPUT DRIVER] Initial Delay %0d is outside 1..%0d",
                       initial_delay, DEPTH);

            $display("[INPUT DRIVER] Initial iDelay=%0d, scheduled changes=%0d",
                     initial_delay, delay_event_count);
        end
    endtask

    task automatic apply_delay_events(input integer input_cycle);
        integer event_index;
        begin
            for (event_index = 0;
                 event_index < delay_event_count;
                 event_index = event_index + 1) begin
                if (delay_event_cycle[event_index] == input_cycle) begin
                    iDelay = delay_event_value[event_index];
                    $display("[INPUT DRIVER] cycle=%0d, iDelay changed to %0d",
                             input_cycle, iDelay);
                end
            end
        end
    endtask

    initial begin : DRIVER_MAIN
        integer vector_index;

        iRsn               = 1'b0;
        iDataEn            = 1'b0;
        iData              = '0;
        iDelay             = '0;
        driver_done        = 1'b0;
        driven_cycle_count = 0;

        if (!$value$plusargs("SCENARIO=%d", scenario_id))
            scenario_id = 2;

        input_filename    = $sformatf("vectors/scenario%0d/Input.txt", scenario_id);
        register_filename = $sformatf("vectors/scenario%0d/register.txt", scenario_id);

        parse_input_file(input_filename);
        parse_register_file(register_filename);

        // Keep active-low reset asserted for three complete negative edges.
        repeat (3) @(negedge iClk);

        // Release reset and present vector 1 before the next rising edge.
        iRsn   = 1'b1;
        iDelay = initial_delay;

        for (vector_index = 0;
             vector_index < data_count;
             vector_index = vector_index + 1) begin
            apply_delay_events(vector_index + 1);
            iData   = data_vector[vector_index];
            iDataEn = valid_vector[vector_index];
            driven_cycle_count = vector_index + 1;
            @(negedge iClk);
        end

        // Flush the memory delay line. The checker decides the exact end point
        // from output.txt, while the driver supplies enough idle clocks.
        iData   = '0;
        iDataEn = 1'b0;
        repeat (DEPTH + 4) @(negedge iClk);

        driver_done = 1'b1;
        $display("[INPUT DRIVER] Scenario %0d drive completed", scenario_id);
    end

endmodule

03_memory_based_dv/rtl/memory_delay_logic.sv
`timescale 1ns/1ps

// -----------------------------------------------------------------------------
// Project 3 DUT: simple dual-port memory based delay logic
// - One write port: stores iData and iDataEn into the current time slot.
// - One read port : reads the slot located iDelay clocks behind write_ptr.
// - When the delayed valid bit is 0, oDataEn becomes 0 and oData holds the
//   most recently accepted output value. This matches the lecture reference
//   vector behavior (for example: 3, 4, 4, 6, 6, 6, 9).
// -----------------------------------------------------------------------------
module memory_delay_logic #(
    parameter integer DATA_WIDTH  = 16,
    parameter integer DEPTH       = 10,
    parameter integer ADDR_WIDTH  = (DEPTH <= 1) ? 1 : $clog2(DEPTH),
    parameter integer DELAY_WIDTH = (DEPTH <= 1) ? 1 : $clog2(DEPTH + 1)
) (
    input  logic                   iClk,
    input  logic                   iRsn,
    input  logic                   iDataEn,
    input  logic [DATA_WIDTH-1:0]  iData,
    input  logic [DELAY_WIDTH-1:0] iDelay,
    output logic                   oDataEn,
    output logic [DATA_WIDTH-1:0]  oData
);

    // The data array is coded as a simple dual-port RAM: one synchronous write
    // port and one synchronous read port. Quartus can map this array to device
    // memory resources when the selected device and synthesis settings allow.
    (* ramstyle = "MLAB" *) logic [DATA_WIDTH-1:0] data_mem [0:DEPTH-1];

    // Valid information is stored in parallel with the data time slots.
    logic valid_mem [0:DEPTH-1];

    logic [ADDR_WIDTH-1:0] write_ptr;
    logic [ADDR_WIDTH-1:0] read_addr;

    integer reset_index;

    // Calculate (write_ptr - iDelay) modulo DEPTH.
    function automatic [ADDR_WIDTH-1:0] calc_read_addr(
        input logic [ADDR_WIDTH-1:0]  wr_ptr,
        input logic [DELAY_WIDTH-1:0] delay_value
    );
        integer tmp_addr;
        integer wr_int;
        integer delay_int;
        begin
            wr_int    = wr_ptr;
            delay_int = delay_value;
            tmp_addr  = wr_int;

            if ((delay_int >= 1) && (delay_int <= DEPTH)) begin
                tmp_addr = wr_int - delay_int;
                if (tmp_addr < 0)
                    tmp_addr = tmp_addr + DEPTH;
            end

            calc_read_addr = tmp_addr[ADDR_WIDTH-1:0];
        end
    endfunction

    always_comb begin
        read_addr = calc_read_addr(write_ptr, iDelay);
    end

    // Write port and circular write-pointer control.
    always_ff @(posedge iClk or negedge iRsn) begin
        if (!iRsn) begin
            write_ptr <= '0;

            // Only the valid array requires deterministic reset. The data RAM
            // is ignored while its corresponding valid bit is 0.
            for (reset_index = 0; reset_index < DEPTH; reset_index = reset_index + 1)
                valid_mem[reset_index] <= 1'b0;
        end
        else begin
            valid_mem[write_ptr] <= iDataEn;

            // Input gating: invalid input cycles do not overwrite data_mem.
            if (iDataEn)
                data_mem[write_ptr] <= iData;

            if (write_ptr == DEPTH - 1)
                write_ptr <= '0;
            else
                write_ptr <= write_ptr + 1'b1;
        end
    end

    // Read port and output gating.
    always_ff @(posedge iClk or negedge iRsn) begin
        if (!iRsn) begin
            oDataEn <= 1'b0;
            oData   <= '0;
        end
        else if ((iDelay >= 1) && (iDelay <= DEPTH)) begin
            oDataEn <= valid_mem[read_addr];

            // Output gating: update oData only for a valid delayed sample.
            // Otherwise oData holds the previous valid value.
            if (valid_mem[read_addr])
                oData <= data_mem[read_addr];
        end
        else begin
            oDataEn <= 1'b0;
        end
    end

endmodule

03_memory_based_dv/tb/tb_memory_delay_logic.sv
`timescale 1ns/1ps

// -----------------------------------------------------------------------------
// Top-level verification environment
//   Input Driver -> DUT -> Output Checker
// -----------------------------------------------------------------------------
module tb_memory_delay_logic;

    localparam integer DATA_WIDTH  = 16;
    localparam integer DEPTH       = 10;
    localparam integer DELAY_WIDTH = $clog2(DEPTH + 1);
    localparam time    CLK_PERIOD  = 10ns;  // 100 MHz

    logic                   iClk;
    logic                   iRsn;
    logic                   iDataEn;
    logic [DATA_WIDTH-1:0]  iData;
    logic [DELAY_WIDTH-1:0] iDelay;
    logic                   oDataEn;
    logic [DATA_WIDTH-1:0]  oData;

    logic   driver_done;
    logic   checker_done;
    integer driven_cycle_count;
    integer error_count;
    integer compared_sample_count;
    integer actual_valid_count;
    integer scenario_id;

    initial begin
        iClk = 1'b0;
        forever #(CLK_PERIOD/2) iClk = ~iClk;
    end

    memory_delay_logic #(
        .DATA_WIDTH (DATA_WIDTH),
        .DEPTH      (DEPTH)
    ) dut (
        .iClk    (iClk),
        .iRsn    (iRsn),
        .iDataEn (iDataEn),
        .iData   (iData),
        .iDelay  (iDelay),
        .oDataEn (oDataEn),
        .oData   (oData)
    );

    input_driver #(
        .DATA_WIDTH (DATA_WIDTH),
        .DEPTH      (DEPTH)
    ) driver (
        .iClk               (iClk),
        .iRsn               (iRsn),
        .iDataEn            (iDataEn),
        .iData              (iData),
        .iDelay             (iDelay),
        .driver_done        (driver_done),
        .driven_cycle_count (driven_cycle_count)
    );

    output_checker #(
        .DATA_WIDTH (DATA_WIDTH)
    ) output_check (
        .iClk                  (iClk),
        .iRsn                  (iRsn),
        .oDataEn               (oDataEn),
        .oData                 (oData),
        .checker_done          (checker_done),
        .error_count           (error_count),
        .compared_sample_count (compared_sample_count),
        .actual_valid_count    (actual_valid_count)
    );

    initial begin : TEST_CONTROL
        if (!$value$plusargs("SCENARIO=%d", scenario_id))
            scenario_id = 2;

        $display("============================================================");
        $display(" Project 3: Memory Based Delay Logic Verification");
        $display(" Scenario %0d", scenario_id);
        $display("============================================================");

        wait (checker_done === 1'b1);
        #10;

        if (error_count == 0) begin
            $display("[TEST PASS] Scenario %0d completed without errors", scenario_id);
            $finish;
        end
        else begin
            $fatal(1, "[TEST FAIL] Scenario %0d, errors=%0d",
                   scenario_id, error_count);
        end
    end

    // Watchdog for malformed files or a stalled test.
    initial begin : WATCHDOG
        #500000;
        $fatal(1, "[WATCHDOG] Simulation timeout");
    end

    // Optional VCD output for batch activity/debug runs.
    initial begin : OPTIONAL_VCD
        if ($test$plusargs("DUMP_VCD")) begin
            $dumpfile("results/memory_delay_logic.vcd");
            $dumpvars(0, tb_memory_delay_logic);
        end
    end

endmodule

03_memory_based_dv/results/scenario2_waveform.vcd
$date
	Wed Jul 29 00:39:16 2026
$end
$version
	Icarus Verilog
$end
$timescale
	1ps
$end
$scope module tb_memory_delay_logic $end
$var wire 1 ! oDataEn $end
$var wire 16 " oData [15:0] $end
$var wire 1 # iRsn $end
$var wire 4 $ iDelay [3:0] $end
$var wire 1 % iDataEn $end
$var wire 16 & iData [15:0] $end
$var wire 32 ' error_count [31:0] $end
$var wire 1 ( driver_done $end
$var wire 32 ) driven_cycle_count [31:0] $end
$var wire 32 * compared_sample_count [31:0] $end
$var wire 1 + checker_done $end
$var wire 32 , actual_valid_count [31:0] $end
$var parameter 64 - CLK_PERIOD $end
$var parameter 32 . DATA_WIDTH $end
$var parameter 32 / DELAY_WIDTH $end
$var parameter 32 0 DEPTH $end
$var reg 1 1 iClk $end
$var integer 32 2 scenario_id [31:0] $end
$scope module driver $end
$var wire 1 1 iClk $end
$var parameter 32 3 DATA_WIDTH $end
$var parameter 32 4 DELAY_WIDTH $end
$var parameter 32 5 DEPTH $end
$var parameter 32 6 MAX_DELAY_EVENTS $end
$var parameter 32 7 MAX_VECTORS $end
$var reg 1 ( driver_done $end
$var reg 16 8 iData [15:0] $end
$var reg 1 % iDataEn $end
$var reg 4 9 iDelay [3:0] $end
$var reg 1 # iRsn $end
$var reg 4 : initial_delay [3:0] $end
$var integer 32 ; data_count [31:0] $end
$var integer 32 < delay_event_count [31:0] $end
$var integer 32 = driven_cycle_count [31:0] $end
$var integer 32 > scenario_id [31:0] $end
$var integer 32 ? valid_count [31:0] $end
$scope begin DRIVER_MAIN $end
$var integer 32 @ vector_index [31:0] $end
$upscope $end
$scope task apply_delay_events $end
$upscope $end
$scope task parse_input_file $end
$upscope $end
$scope task parse_register_file $end
$upscope $end
$upscope $end
$scope module dut $end
$var wire 1 1 iClk $end
$var wire 16 A iData [15:0] $end
$var wire 1 % iDataEn $end
$var wire 4 B iDelay [3:0] $end
$var wire 1 # iRsn $end
$var parameter 32 C ADDR_WIDTH $end
$var parameter 32 D DATA_WIDTH $end
$var parameter 32 E DELAY_WIDTH $end
$var parameter 32 F DEPTH $end
$var reg 16 G oData [15:0] $end
$var reg 1 ! oDataEn $end
$var reg 4 H read_addr [3:0] $end
$var reg 4 I write_ptr [3:0] $end
$var integer 32 J reset_index [31:0] $end
$scope function calc_read_addr $end
$upscope $end
$upscope $end
$scope module output_check $end
$var wire 1 1 iClk $end
$var wire 1 # iRsn $end
$var wire 16 K oData [15:0] $end
$var wire 1 ! oDataEn $end
$var parameter 32 L DATA_WIDTH $end
$var parameter 32 M MAX_VECTORS $end
$var reg 1 + checker_done $end
$var integer 32 N actual_valid_count [31:0] $end
$var integer 32 O compared_sample_count [31:0] $end
$var integer 32 P error_count [31:0] $end
$var integer 32 Q expected_data_count [31:0] $end
$var integer 32 R expected_valid_count [31:0] $end
$var integer 32 S expected_valid_vector_count [31:0] $end
$var integer 32 T scenario_id [31:0] $end
$scope begin CHECKER_MAIN $end
$var integer 32 U log_fd [31:0] $end
$var integer 32 V sample_index [31:0] $end
$upscope $end
$scope task parse_output_file $end
$upscope $end
$upscope $end
$scope begin OPTIONAL_VCD $end
$upscope $end
$scope begin TEST_CONTROL $end
$upscope $end
$scope begin WATCHDOG $end
$upscope $end
$upscope $end
$enddefinitions $end
$comment Show the parameter values. $end
$dumpall
b100000000000 M
b10000 L
b1010 F
b100 E
b10000 D
b100 C
b10000000000 7
b100000 6
b1010 5
b100 4
b10000 3
b1010 0
b100 /
b10000 .
b1010 -
$end
#0
$dumpvars
bx V
b10000000000000000000000000000011 U
b10 T
b1110 S
b100 R
b1110 Q
b0 P
b0 O
b0 N
b0 K
b1010 J
b0 I
b0 H
b0 G
b0 B
b0 A
bx @
b1001 ?
b10 >
b0 =
b0 <
b1001 ;
b101 :
b0 9
b0 8
b10 2
01
b0 ,
0+
b0 *
b0 )
0(
b0 '
b0 &
0%
b0 $
0#
b0 "
0!
$end
#5000
b1010 J
11
#10000
01
#15000
b1010 J
11
#20000
b101 H
b0 V
b1 )
b1 =
b1 &
b1 8
b1 A
b0 @
b101 $
b101 9
b101 B
1#
01
#25000
b110 H
b1 I
11
#26000
b1 V
b1 *
b1 O
#30000
b10 )
b10 =
b10 &
b10 8
b10 A
b1 @
01
#35000
b111 H
b10 I
11
#36000
b10 V
b10 *
b10 O
#40000
b11 )
b11 =
1%
b11 &
b11 8
b11 A
b10 @
01
#45000
b1000 H
b11 I
11
#46000
b11 V
b11 *
b11 O
#50000
b100 )
b100 =
b100 &
b100 8
b100 A
b11 @
01
#55000
b1001 H
b100 I
11
#56000
b100 V
b100 *
b100 O
#60000
b101 )
b101 =
0%
b101 &
b101 8
b101 A
b100 @
01
#65000
b0 H
b101 I
11
#66000
b101 V
b101 *
b101 O
#70000
b110 )
b110 =
1%
b110 &
b110 8
b110 A
b101 @
01
#75000
b1 H
b110 I
11
#76000
b110 V
b110 *
b110 O
#80000
b111 )
b111 =
0%
b111 &
b111 8
b111 A
b110 @
01
#85000
b10 H
b111 I
11
#86000
b111 V
b111 *
b111 O
#90000
b1000 )
b1000 =
b1000 &
b1000 8
b1000 A
b111 @
01
#95000
b11 H
b1000 I
b11 "
b11 G
b11 K
1!
11
#96000
b1000 V
b1 ,
b1 N
b1000 *
b1000 O
#100000
b1001 )
b1001 =
1%
b1001 &
b1001 8
b1001 A
b1000 @
01
#105000
b100 H
b100 "
b100 G
b100 K
b1001 I
11
#106000
b1001 V
b10 ,
b10 N
b1001 *
b1001 O
#110000
0%
b0 &
b0 8
b0 A
b1001 @
01
#115000
b101 H
b0 I
0!
11
#116000
b1010 V
b1010 *
b1010 O
#120000
01
#125000
b110 H
b110 "
b110 G
b110 K
1!
b1 I
11
#126000
b1011 V
b11 ,
b11 N
b1011 *
b1011 O
#130000
01
#135000
b111 H
b10 I
0!
11
#136000
b1100 V
b1100 *
b1100 O
#140000
01
#145000
b1000 H
b11 I
11
#146000
b1101 V
b1101 *
b1101 O
#150000
01
#155000
b1001 H
b100 I
b1001 "
b1001 G
b1001 K
1!
11
#156000
1+
b1110 V
b100 ,
b100 N
b1110 *
b1110 O
#160000
01
#165000
b0 H
0!
b101 I
11
