02_circular_queue_ppa/rtl/circular_queue_delay_logic.sv
`timescale 1ns/1ps

// -----------------------------------------------------------------------------
// Circular Queue based programmable delay logic
// - iDelay = N: outputs the input/valid pair stored N clock edges earlier.
// - iDataEn gates the input slot.
// - oDataEn gates oData; invalid output slots are forced to zero.
// - The data memory is intentionally not reset. valid_mem is reset, so stale
//   memory contents can never be observed as valid data. This also allows the
//   storage array to map efficiently to FPGA memory resources.
// -----------------------------------------------------------------------------
module circular_queue_delay_logic #(
    parameter int DATA_WIDTH  = 16,
    parameter int DEPTH       = 10,
    parameter int PTR_WIDTH   = (DEPTH <= 2) ? 1 : $clog2(DEPTH),
    parameter int DELAY_WIDTH = (DEPTH <= 1) ? 1 : $clog2(DEPTH + 1)
)(
    input  logic                   iClk,
    input  logic                   iRsn,
    input  logic                   iDataEn,
    input  logic [DATA_WIDTH-1:0]  iData,
    input  logic [DELAY_WIDTH-1:0] iDelay,
    output logic                   oDataEn,
    output logic [DATA_WIDTH-1:0]  oData
);

    // The queue stores one data word and one valid bit per clock slot.
    // Quartus may infer distributed memory/MLAB depending on DEPTH and device.
    logic [DATA_WIDTH-1:0] data_mem [0:DEPTH-1];
    logic [DEPTH-1:0]      valid_mem;

    logic [PTR_WIDTH-1:0] write_ptr;
    logic [PTR_WIDTH-1:0] read_ptr;
    logic                 delay_is_valid;

    integer read_index_int;

    // Read address = current write pointer - iDelay (mod DEPTH).
    // write_ptr points to the slot that will receive the next input word.
    always_comb begin
        read_index_int = 0;
        read_ptr       = '0;
        delay_is_valid = 1'b0;

        if ((iDelay >= 1) && (iDelay <= DEPTH)) begin
            delay_is_valid = 1'b1;
            if (write_ptr >= iDelay) begin
                read_index_int = write_ptr - iDelay;
            end else begin
                read_index_int = write_ptr + DEPTH - iDelay;
            end
            read_ptr = read_index_int[PTR_WIDTH-1:0];
        end
    end

    // Circular write operation: only one queue entry is updated each clock.
    always_ff @(posedge iClk or negedge iRsn) begin
        if (!iRsn) begin
            write_ptr <= '0;
            valid_mem <= '0;
        end else begin
            data_mem[write_ptr]  <= iDataEn ? iData : '0;
            valid_mem[write_ptr] <= iDataEn;

            if (write_ptr == DEPTH-1) begin
                write_ptr <= '0;
            end else begin
                write_ptr <= write_ptr + 1'b1;
            end
        end
    end

    // Output gating: invalid queue slots never propagate stale data.
    always_comb begin
        oDataEn = 1'b0;
        oData   = '0;

        if (iRsn && delay_is_valid) begin
            oDataEn = valid_mem[read_ptr];
            oData   = valid_mem[read_ptr] ? data_mem[read_ptr] : '0;
        end
    end

endmodule

02_circular_queue_ppa/rtl/shift_register_delay_logic_ppa.sv
`timescale 1ns/1ps

// -----------------------------------------------------------------------------
// Parameterized Shift Register delay logic used only for Project 1 vs Project 2
// PPA comparison. The functional behavior and stimulus are kept equivalent to
// circular_queue_delay_logic.
// -----------------------------------------------------------------------------
module shift_register_delay_logic_ppa #(
    parameter int DATA_WIDTH  = 16,
    parameter int DEPTH       = 10,
    parameter int DELAY_WIDTH = (DEPTH <= 1) ? 1 : $clog2(DEPTH + 1)
)(
    input  logic                   iClk,
    input  logic                   iRsn,
    input  logic                   iDataEn,
    input  logic [DATA_WIDTH-1:0]  iData,
    input  logic [DELAY_WIDTH-1:0] iDelay,
    output logic                   oDataEn,
    output logic [DATA_WIDTH-1:0]  oData
);

    logic [DATA_WIDTH-1:0] data_shift [0:DEPTH-1];
    logic [DEPTH-1:0]      valid_shift;
    integer stage;

    // Every stored word shifts each clock. This is the main source of the
    // dynamic-power difference compared with the circular queue architecture.
    always_ff @(posedge iClk or negedge iRsn) begin
        if (!iRsn) begin
            valid_shift <= '0;
            for (stage = 0; stage < DEPTH; stage = stage + 1) begin
                data_shift[stage] <= '0;
            end
        end else begin
            for (stage = DEPTH-1; stage > 0; stage = stage - 1) begin
                data_shift[stage]  <= data_shift[stage-1];
                valid_shift[stage] <= valid_shift[stage-1];
            end
            data_shift[0]  <= iDataEn ? iData : '0;
            valid_shift[0] <= iDataEn;
        end
    end

    always_comb begin
        oDataEn = 1'b0;
        oData   = '0;

        if (iRsn && (iDelay >= 1) && (iDelay <= DEPTH)) begin
            oDataEn = valid_shift[iDelay-1];
            oData   = valid_shift[iDelay-1] ? data_shift[iDelay-1] : '0;
        end
    end

endmodule

02_circular_queue_ppa/tb/tb_architecture_equivalence_regression.sv
`timescale 1ns/1ps

// Portable equivalence regression for Project 2. Both implementations are
// checked against an independent transaction-history model.
module tb_architecture_equivalence_regression;
    localparam integer DATA_WIDTH = 16;
    localparam integer DEPTH = 10;
    localparam integer DELAY_WIDTH = 4;
    localparam time CLK_PERIOD = 10ns;

    logic iClk = 1'b0;
    logic iRsn = 1'b0;
    logic iDataEn = 1'b0;
    logic [DATA_WIDTH-1:0] iData = '0;
    logic [DELAY_WIDTH-1:0] iDelay = 4'd3;
    logic shift_oDataEn;
    logic [DATA_WIDTH-1:0] shift_oData;
    logic circular_oDataEn;
    logic [DATA_WIDTH-1:0] circular_oData;

    logic [DATA_WIDTH-1:0] reference_data [0:DEPTH-1];
    logic [DEPTH-1:0] reference_valid;
    integer checks = 0;
    integer errors = 0;
    integer stage;

    shift_register_delay_logic_ppa #(
        .DATA_WIDTH(DATA_WIDTH),
        .DEPTH(DEPTH),
        .DELAY_WIDTH(DELAY_WIDTH)
    ) shift_dut (
        .iClk(iClk), .iRsn(iRsn), .iDataEn(iDataEn), .iData(iData),
        .iDelay(iDelay), .oDataEn(shift_oDataEn), .oData(shift_oData)
    );

    circular_queue_delay_logic #(
        .DATA_WIDTH(DATA_WIDTH),
        .DEPTH(DEPTH),
        .DELAY_WIDTH(DELAY_WIDTH)
    ) circular_dut (
        .iClk(iClk), .iRsn(iRsn), .iDataEn(iDataEn), .iData(iData),
        .iDelay(iDelay), .oDataEn(circular_oDataEn), .oData(circular_oData)
    );

    always #(CLK_PERIOD/2) iClk = ~iClk;

    task automatic drive(
        input logic en,
        input logic [DATA_WIDTH-1:0] data,
        input logic [DELAY_WIDTH-1:0] delay_value
    );
        begin
            @(negedge iClk);
            iDataEn = en;
            iData = data;
            iDelay = delay_value;
        end
    endtask

    always @(posedge iClk) begin
        if (!iRsn) begin
            reference_valid = '0;
            for (stage = 0; stage < DEPTH; stage = stage + 1)
                reference_data[stage] = '0;
        end
        else begin
            for (stage = DEPTH-1; stage > 0; stage = stage - 1) begin
                reference_data[stage] = reference_data[stage-1];
                reference_valid[stage] = reference_valid[stage-1];
            end
            reference_data[0] = iDataEn ? iData : '0;
            reference_valid[0] = iDataEn;
        end

        #1;
        if (iRsn) begin : CHECK_OUTPUTS
            logic expected_valid;
            logic [DATA_WIDTH-1:0] expected_data;
            expected_valid = ((iDelay >= 1) && (iDelay <= DEPTH)) ?
                             reference_valid[iDelay-1] : 1'b0;
            expected_data = expected_valid ? reference_data[iDelay-1] : '0;
            checks = checks + 1;

            if ((shift_oDataEn !== expected_valid) ||
                (shift_oData !== expected_data) ||
                (circular_oDataEn !== expected_valid) ||
                (circular_oData !== expected_data)) begin
                errors = errors + 1;
                $display(
                    "[P2][ERROR] check=%0d delay=%0d expected=%0b/%04h shift=%0b/%04h circular=%0b/%04h",
                    checks, iDelay, expected_valid, expected_data,
                    shift_oDataEn, shift_oData, circular_oDataEn, circular_oData
                );
            end
        end
    end

    initial begin
        $dumpfile("results/project2_waveform.vcd");
        $dumpvars(0, tb_architecture_equivalence_regression);

        repeat (3) @(negedge iClk);
        iRsn = 1'b1;

        drive(1'b1, 16'h1101, 4'd3);
        drive(1'b1, 16'h1102, 4'd3);
        drive(1'b1, 16'h1103, 4'd3);
        drive(1'b0, 16'h0000, 4'd3);
        drive(1'b1, 16'h2201, 4'd3);
        drive(1'b0, 16'h0000, 4'd3);

        // Exercise changing delays and a full-depth wrap.
        drive(1'b1, 16'h3301, 4'd2);
        drive(1'b1, 16'h3302, 4'd2);
        drive(1'b1, 16'h4401, 4'd5);
        drive(1'b0, 16'h0000, 4'd5);
        drive(1'b1, 16'h5501, 4'd10);
        drive(1'b1, 16'h5502, 4'd10);
        repeat (13) drive(1'b0, 16'h0000, 4'd10);

        @(posedge iClk);
        #2;
        if (errors == 0)
            $display("[P2][PASS] checks=%0d errors=0; shift and circular implementations match the reference model", checks);
        else
            $display("[P2][FAIL] checks=%0d errors=%0d", checks, errors);
        $finish_and_return(errors == 0 ? 0 : 1);
    end
endmodule

02_circular_queue_ppa/results/project2_waveform.vcd
$date
	Wed Jul 29 22:59:32 2026
$end
$version
	Icarus Verilog
$end
$timescale
	1ps
$end
$scope module tb_architecture_equivalence_regression $end
$var wire 1 ! shift_oDataEn $end
$var wire 16 " shift_oData [15:0] $end
$var wire 1 # circular_oDataEn $end
$var wire 16 $ circular_oData [15:0] $end
$var parameter 64 % CLK_PERIOD $end
$var parameter 32 & DATA_WIDTH $end
$var parameter 32 ' DELAY_WIDTH $end
$var parameter 32 ( DEPTH $end
$var reg 1 ) iClk $end
$var reg 16 * iData [15:0] $end
$var reg 1 + iDataEn $end
$var reg 4 , iDelay [3:0] $end
$var reg 1 - iRsn $end
$var reg 10 . reference_valid [9:0] $end
$var integer 32 / checks [31:0] $end
$var integer 32 0 errors [31:0] $end
$var integer 32 1 stage [31:0] $end
$scope module circular_dut $end
$var wire 1 ) iClk $end
$var wire 16 2 iData [15:0] $end
$var wire 1 + iDataEn $end
$var wire 4 3 iDelay [3:0] $end
$var wire 1 - iRsn $end
$var parameter 32 4 DATA_WIDTH $end
$var parameter 32 5 DELAY_WIDTH $end
$var parameter 32 6 DEPTH $end
$var parameter 32 7 PTR_WIDTH $end
$var reg 1 8 delay_is_valid $end
$var reg 16 9 oData [15:0] $end
$var reg 1 # oDataEn $end
$var reg 4 : read_ptr [3:0] $end
$var reg 10 ; valid_mem [9:0] $end
$var reg 4 < write_ptr [3:0] $end
$var integer 32 = read_index_int [31:0] $end
$upscope $end
$scope module shift_dut $end
$var wire 1 ) iClk $end
$var wire 16 > iData [15:0] $end
$var wire 1 + iDataEn $end
$var wire 4 ? iDelay [3:0] $end
$var wire 1 - iRsn $end
$var parameter 32 @ DATA_WIDTH $end
$var parameter 32 A DELAY_WIDTH $end
$var parameter 32 B DEPTH $end
$var reg 16 C oData [15:0] $end
$var reg 1 ! oDataEn $end
$var reg 10 D valid_shift [9:0] $end
$var integer 32 E stage [31:0] $end
$upscope $end
$scope begin CHECK_OUTPUTS $end
$var reg 16 F expected_data [15:0] $end
$var reg 1 G expected_valid $end
$upscope $end
$scope task drive $end
$upscope $end
$upscope $end
$enddefinitions $end
$comment Show the parameter values. $end
$dumpall
b1010 B
b100 A
b10000 @
b100 7
b1010 6
b100 5
b10000 4
b1010 (
b100 '
b10000 &
b1010 %
$end
#0
$dumpvars
xG
bx F
bx E
bx D
b0 C
b11 ?
b0 >
bx =
bx <
bx ;
bx :
b0 9
18
b11 3
b0 2
bx 1
b0 0
b0 /
bx .
0-
b11 ,
0+
b0 *
0)
b0 $
0#
b0 "
0!
$end
#5000
18
b111 :
b111 =
b0 D
b0 ;
b0 <
b1010 E
b1010 1
b0 .
1)
#10000
0)
#15000
b1010 E
b1010 1
1)
#20000
0)
#25000
b1010 E
b1010 1
1)
#30000
1-
0)
#35000
18
b1000 :
b1000 =
b1 <
b0 E
b0 1
1)
#36000
b1 /
b0 F
0G
#40000
b1000100000001 *
b1000100000001 2
b1000100000001 >
1+
0)
#45000
18
b1001 :
b1001 =
b1 D
b10 <
b10 ;
b0 E
b1 .
b0 1
1)
#46000
b10 /
#50000
b1000100000010 *
b1000100000010 2
b1000100000010 >
0)
#55000
18
b0 :
b0 =
b11 <
b110 ;
b11 D
b0 E
b11 .
b0 1
1)
#56000
b11 /
#60000
b1000100000011 *
b1000100000011 2
b1000100000011 >
0)
#65000
b1000100000001 $
b1000100000001 9
1#
b1000100000001 "
b1000100000001 C
1!
b1 :
b1 =
18
b111 D
b100 <
b1110 ;
b0 E
b111 .
b0 1
1)
#66000
b100 /
b1000100000001 F
1G
#70000
b0 *
b0 2
b0 >
0+
0)
#75000
18
b10 :
b10 =
b1000100000010 $
b1000100000010 9
1#
b1000100000010 "
b1000100000010 C
1!
b101 <
b1110 D
b0 E
b1110 .
b0 1
1)
#76000
b101 /
b1000100000010 F
#80000
b10001000000001 *
b10001000000001 2
b10001000000001 >
1+
0)
#85000
b1000100000011 "
b1000100000011 C
1!
18
b11 :
b11 =
b1000100000011 $
b1000100000011 9
1#
b11101 D
b110 <
b101110 ;
b0 E
b11101 .
b0 1
1)
#86000
b110 /
b1000100000011 F
#90000
b0 *
b0 2
b0 >
0+
0)
#95000
18
b100 :
b100 =
b0 $
b0 9
0#
b0 "
b0 C
0!
b111 <
b111010 D
b0 E
b111010 .
b0 1
1)
#96000
b111 /
b0 F
0G
#100000
b10001000000001 $
b10001000000001 9
1#
18
b101 :
b101 =
b10001000000001 "
b10001000000001 C
1!
b10 ,
b10 3
b10 ?
b11001100000001 *
b11001100000001 2
b11001100000001 >
1+
0)
#105000
b0 "
b0 C
0!
18
b110 :
b110 =
b0 $
b0 9
0#
b1110101 D
b1000 <
b10101110 ;
b0 E
b1110101 .
b0 1
1)
#106000
b1000 /
#110000
b11001100000010 *
b11001100000010 2
b11001100000010 >
0)
#115000
b11001100000001 $
b11001100000001 9
1#
18
b111 :
b111 =
b11001100000001 "
b11001100000001 C
1!
b1001 <
b110101110 ;
b11101011 D
b0 E
b11101011 .
b0 1
1)
#116000
b1001 /
b11001100000001 F
1G
#120000
b0 $
b0 9
0#
18
b100 :
b100 =
b0 "
b0 C
0!
b101 ,
b101 3
b101 ?
b100010000000001 *
b100010000000001 2
b100010000000001 >
0)
#125000
b10001000000001 $
b10001000000001 9
1#
b10001000000001 "
b10001000000001 C
1!
18
b101 :
b101 =
b111010111 D
b0 <
b1110101110 ;
b0 E
b111010111 .
b0 1
1)
#126000
b1010 /
b10001000000001 F
#130000
b0 *
b0 2
b0 >
0+
0)
#135000
b0 $
b0 9
0#
18
b110 :
b110 =
b0 "
b0 C
0!
b1 <
b1110101110 D
b0 E
b1110101110 .
b0 1
1)
#136000
b1011 /
b0 F
0G
#140000
b1000100000001 $
b1000100000001 9
1#
18
b1 :
b1 =
b1000100000001 "
b1000100000001 C
1!
b1010 ,
b1010 3
b1010 ?
b101010100000001 *
b101010100000001 2
b101010100000001 >
1+
0)
#145000
b1000100000010 "
b1000100000010 C
1!
18
b10 :
b10 =
b1000100000010 $
b1000100000010 9
1#
b1101011101 D
b10 <
b0 E
b1101011101 .
b0 1
1)
#146000
b1100 /
b1000100000010 F
1G
#150000
b101010100000010 *
b101010100000010 2
b101010100000010 >
0)
#155000
18
b11 :
b11 =
b1000100000011 $
b1000100000011 9
1#
b1000100000011 "
b1000100000011 C
1!
b11 <
b1010111011 D
b0 E
b1010111011 .
b0 1
1)
#156000
b1101 /
b1000100000011 F
#160000
b0 *
b0 2
b0 >
0+
0)
#165000
b0 "
b0 C
0!
18
b100 :
b100 =
b0 $
b0 9
0#
b101110110 D
b100 <
b1110100110 ;
b0 E
b101110110 .
b0 1
1)
#166000
b1110 /
b0 F
0G
#170000
0)
#175000
b10001000000001 $
b10001000000001 9
1#
18
b101 :
b101 =
b10001000000001 "
b10001000000001 C
1!
b101 <
b1011101100 D
b0 E
b1011101100 .
b0 1
1)
#176000
b1111 /
b10001000000001 F
1G
#180000
0)
#185000
b0 "
b0 C
0!
18
b110 :
b110 =
b0 $
b0 9
0#
b111011000 D
b110 <
b1110000110 ;
b0 E
b111011000 .
b0 1
1)
#186000
b10000 /
b0 F
0G
#190000
0)
#195000
b11001100000001 $
b11001100000001 9
1#
18
b111 :
b111 =
b11001100000001 "
b11001100000001 C
1!
b111 <
b1110110000 D
b0 E
b1110110000 .
b0 1
1)
#196000
b10001 /
b11001100000001 F
1G
#200000
0)
#205000
b11001100000010 "
b11001100000010 C
1!
18
b1000 :
b1000 =
b11001100000010 $
b11001100000010 9
1#
b1101100000 D
b1000 <
b1100000110 ;
b0 E
b1101100000 .
b0 1
1)
#206000
b10010 /
b11001100000010 F
#210000
0)
#215000
18
b1001 :
b1001 =
b100010000000001 $
b100010000000001 9
1#
b100010000000001 "
b100010000000001 C
1!
b1001 <
b1000000110 ;
b1011000000 D
b0 E
b1011000000 .
b0 1
1)
#216000
b10011 /
b100010000000001 F
#220000
0)
#225000
b0 "
b0 C
0!
18
b0 :
b0 =
b0 $
b0 9
0#
b110000000 D
b0 <
b110 ;
b0 E
b110000000 .
b0 1
1)
#226000
b10100 /
b0 F
0G
#230000
0)
#235000
b101010100000001 $
b101010100000001 9
1#
b1 :
b1 =
18
b101010100000001 "
b101010100000001 C
1!
b1 <
b1100000000 D
b0 E
b1100000000 .
b0 1
1)
#236000
b10101 /
b101010100000001 F
1G
#240000
0)
#245000
b101010100000010 "
b101010100000010 C
1!
18
b10 :
b10 =
b101010100000010 $
b101010100000010 9
1#
b1000000000 D
b10 <
b100 ;
b0 E
b1000000000 .
b0 1
1)
#246000
b10110 /
b101010100000010 F
#250000
0)
#255000
18
b11 :
b11 =
b0 $
b0 9
0#
b0 "
b0 C
0!
b11 <
b0 ;
b0 D
b0 E
b0 .
b0 1
1)
#256000
b10111 /
b0 F
0G
#260000
0)
#265000
18
b100 :
b100 =
b100 <
b0 E
b0 1
1)
#266000
b11000 /
#270000
0)
#275000
18
b101 :
b101 =
b101 <
b0 E
b0 1
1)
#276000
b11001 /
#280000
0)
#285000
18
b110 :
b110 =
b110 <
b0 E
b0 1
1)
#286000
b11010 /
