01_shift_register_baseline/rtl/delay_logic.sv
`timescale 1ns/1ps

module delay_logic #(
    parameter int DATA_WIDTH = 16,
    parameter int DEPTH      = 10
)(
    input  logic                  iClk,
    input  logic                  iRsn,
    input  logic                  iDataEn,
    input  logic [DATA_WIDTH-1:0] iData,
    input  logic [2:0]            iDelay,
    output logic                  oDataEn,
    output logic [DATA_WIDTH-1:0] oData
);

    logic [DATA_WIDTH-1:0] data_shift [0:DEPTH-1];
    logic [DEPTH-1:0]      enable_shift;
    integer stage;

    // Shift-register datapath and enable pipeline
    always_ff @(posedge iClk or negedge iRsn) begin
        if (!iRsn) begin
            enable_shift <= '0;
            for (stage = 0; stage < DEPTH; stage = stage + 1) begin
                data_shift[stage] <= '0;
            end
        end else begin
            for (stage = DEPTH-1; stage > 0; stage = stage - 1) begin
                data_shift[stage]  <= data_shift[stage-1];
                enable_shift[stage] <= enable_shift[stage-1];
            end

            // Input gating by iDataEn
            data_shift[0]  <= iDataEn ? iData : '0;
            enable_shift[0] <= iDataEn;
        end
    end

    // Select the delayed tap. The lecture material defines iDelay as [2:0].
    // iDelay=0 is not used by the supplied verification scenarios.
    always_comb begin
        oDataEn = 1'b0;
        oData   = '0;

        if (iRsn && (iDelay != 3'd0)) begin
            oDataEn = enable_shift[iDelay-1];
            oData   = enable_shift[iDelay-1] ? data_shift[iDelay-1] : '0;
        end
    end

endmodule

01_shift_register_baseline/tb/tb_delay_logic.sv
`timescale 1ns/1ps

module tb_delay_logic;

    localparam int DATA_WIDTH = 16;
    localparam int DEPTH      = 10;
    localparam time CLK_PERIOD = 10ns;

    logic                  iClk;
    logic                  iRsn;
    logic                  iDataEn;
    logic [DATA_WIDTH-1:0] iData;
    logic [2:0]            iDelay;
    logic                  oDataEn;
    logic [DATA_WIDTH-1:0] oData;

    delay_logic #(
        .DATA_WIDTH(DATA_WIDTH),
        .DEPTH(DEPTH)
    ) dut (
        .iClk(iClk),
        .iRsn(iRsn),
        .iDataEn(iDataEn),
        .iData(iData),
        .iDelay(iDelay),
        .oDataEn(oDataEn),
        .oData(oData)
    );

    initial iClk = 1'b0;
    always #(CLK_PERIOD/2) iClk = ~iClk;

    task automatic drive_cycle(
        input logic                  en,
        input logic [DATA_WIDTH-1:0] data,
        input logic [2:0]            delay_value
    );
        begin
            @(negedge iClk);
            iDataEn = en;
            iData   = data;
            iDelay  = delay_value;
        end
    endtask

    initial begin
        iRsn    = 1'b0;
        iDataEn = 1'b0;
        iData   = '0;
        iDelay  = 3'd3;

        // Scenario 1: reset asserted and then released
        repeat (3) @(negedge iClk);
        iRsn = 1'b1;
        drive_cycle(1'b0, 16'h0000, 3'd3);
        drive_cycle(1'b0, 16'h0000, 3'd3);

        // Scenario 2: continuous Enable input, fixed iDelay=3
        drive_cycle(1'b1, 16'h1001, 3'd3);
        drive_cycle(1'b1, 16'h1002, 3'd3);
        drive_cycle(1'b1, 16'h1003, 3'd3);
        drive_cycle(1'b1, 16'h1004, 3'd3);
        drive_cycle(1'b1, 16'h1005, 3'd3);
        drive_cycle(1'b1, 16'h1006, 3'd3);
        drive_cycle(1'b0, 16'h0000, 3'd3);
        drive_cycle(1'b0, 16'h0000, 3'd3);
        drive_cycle(1'b0, 16'h0000, 3'd3);
        drive_cycle(1'b0, 16'h0000, 3'd3);

        // Scenario 3: change the delay value during operation (optional scenario)
        drive_cycle(1'b1, 16'h2001, 3'd2);
        drive_cycle(1'b1, 16'h2002, 3'd2);
        drive_cycle(1'b1, 16'h2003, 3'd2);
        drive_cycle(1'b1, 16'h2004, 3'd2);
        drive_cycle(1'b1, 16'h3001, 3'd5);
        drive_cycle(1'b1, 16'h3002, 3'd5);
        drive_cycle(1'b1, 16'h3003, 3'd5);
        drive_cycle(1'b1, 16'h3004, 3'd5);
        drive_cycle(1'b0, 16'h0000, 3'd5);
        drive_cycle(1'b0, 16'h0000, 3'd5);
        drive_cycle(1'b0, 16'h0000, 3'd5);
        drive_cycle(1'b0, 16'h0000, 3'd5);
        drive_cycle(1'b0, 16'h0000, 3'd5);
        drive_cycle(1'b0, 16'h0000, 3'd5);

        #20;
        $finish;
    end

endmodule

results/archive_rerun/project1_original.vcd
$date
	Wed Jul 29 22:58:47 2026
$end
$version
	ModelSim Version 10.5b
$end
$timescale
	1ps
$end

$scope module tb_delay_logic $end
$var parameter 32 ! DATA_WIDTH $end
$var parameter 32 " DEPTH $end
$var parameter 64 # CLK_PERIOD $end
$var reg 1 $ iClk $end
$var reg 1 % iRsn $end
$var reg 1 & iDataEn $end
$var reg 16 ' iData [15:0] $end
$var reg 3 ( iDelay [2:0] $end
$var reg 1 ) oDataEn $end
$var reg 16 * oData [15:0] $end

$scope module dut $end
$var parameter 32 + DATA_WIDTH $end
$var parameter 32 , DEPTH $end
$var wire 1 - iClk $end
$var wire 1 . iRsn $end
$var wire 1 / iDataEn $end
$var wire 1 0 iData [15] $end
$var wire 1 1 iData [14] $end
$var wire 1 2 iData [13] $end
$var wire 1 3 iData [12] $end
$var wire 1 4 iData [11] $end
$var wire 1 5 iData [10] $end
$var wire 1 6 iData [9] $end
$var wire 1 7 iData [8] $end
$var wire 1 8 iData [7] $end
$var wire 1 9 iData [6] $end
$var wire 1 : iData [5] $end
$var wire 1 ; iData [4] $end
$var wire 1 < iData [3] $end
$var wire 1 = iData [2] $end
$var wire 1 > iData [1] $end
$var wire 1 ? iData [0] $end
$var wire 1 @ iDelay [2] $end
$var wire 1 A iDelay [1] $end
$var wire 1 B iDelay [0] $end
$var reg 1 C oDataEn $end
$var reg 16 D oData [15:0] $end
$var reg 10 E enable_shift [9:0] $end
$var integer 32 F stage $end
$upscope $end
$upscope $end
$enddefinitions $end
#0
$dumpvars
0$
0%
0&
b0 '
b11 (
0)
b0 *
0C
b0 D
b0 E
b10000 !
b1010 "
b1010 #
b10000 +
b1010 ,
b1010 F
0-
0.
0/
0?
0>
0=
0<
0;
0:
09
08
07
06
05
04
03
02
01
00
1B
1A
0@
$end
#5000
1$
1-
b0 F
b1 F
b10 F
b11 F
b100 F
b101 F
b110 F
b111 F
b1000 F
b1001 F
b1010 F
#10000
0$
0-
#15000
1$
1-
b0 F
b1 F
b10 F
b11 F
b100 F
b101 F
b110 F
b111 F
b1000 F
b1001 F
b1010 F
#20000
0$
0-
#25000
1$
1-
b0 F
b1 F
b10 F
b11 F
b100 F
b101 F
b110 F
b111 F
b1000 F
b1001 F
b1010 F
#30000
0$
0-
1%
1.
#35000
1$
1-
b1001 F
b1000 F
b111 F
b110 F
b101 F
b100 F
b11 F
b10 F
b1 F
b0 F
#40000
0$
0-
#45000
1$
1-
b1001 F
b1000 F
b111 F
b110 F
b101 F
b100 F
b11 F
b10 F
b1 F
b0 F
#50000
0$
0-
#55000
1$
1-
b1001 F
b1000 F
b111 F
b110 F
b101 F
b100 F
b11 F
b10 F
b1 F
b0 F
#60000
0$
0-
1&
b1000000000001 '
1/
1?
13
#65000
1$
1-
b1001 F
b1000 F
b111 F
b110 F
b101 F
b100 F
b11 F
b10 F
b1 F
b0 F
b1 E
#70000
0$
0-
b1000000000010 '
0?
1>
#75000
1$
1-
b1001 F
b1000 F
b111 F
b110 F
b101 F
b100 F
b11 F
b10 F
b1 F
b0 F
b11 E
#80000
0$
0-
b1000000000011 '
1?
#85000
1$
1-
b1001 F
b1000 F
b111 F
b110 F
b101 F
b100 F
b11 F
b10 F
b1 F
b0 F
b111 E
1C
b1000000000001 D
b1000000000001 *
1)
#90000
0$
0-
b1000000000100 '
0?
0>
1=
#95000
1$
1-
b1001 F
b1000 F
b111 F
b110 F
b101 F
b100 F
b11 F
b10 F
b1 F
b0 F
b1111 E
0C
b0 D
1C
b1000000000010 D
b1000000000010 *
#100000
0$
0-
b1000000000101 '
1?
#105000
1$
1-
b1001 F
b1000 F
b111 F
b110 F
b101 F
b100 F
b11 F
b10 F
b1 F
b0 F
b11111 E
0C
b0 D
1C
b1000000000011 D
b1000000000011 *
#110000
0$
0-
b1000000000110 '
0?
1>
#115000
1$
1-
b1001 F
b1000 F
b111 F
b110 F
b101 F
b100 F
b11 F
b10 F
b1 F
b0 F
b111111 E
0C
b0 D
1C
b1000000000100 D
b1000000000100 *
#120000
0$
0-
0&
b0 '
0/
0>
0=
03
#125000
1$
1-
b1001 F
b1000 F
b111 F
b110 F
b101 F
b100 F
b11 F
b10 F
b1 F
b0 F
b1111111 E
b1111110 E
0C
b0 D
1C
b1000000000101 D
b1000000000101 *
#130000
0$
0-
#135000
1$
1-
b1001 F
b1000 F
b111 F
b110 F
b101 F
b100 F
b11 F
b10 F
b1 F
b0 F
b11111110 E
b11111100 E
0C
b0 D
1C
b1000000000110 D
b1000000000110 *
#140000
0$
0-
#145000
1$
1-
b1001 F
b1000 F
b111 F
b110 F
b101 F
b100 F
b11 F
b10 F
b1 F
b0 F
b111111100 E
b111111000 E
0C
b0 D
b0 *
0)
#150000
0$
0-
#155000
1$
1-
b1001 F
b1000 F
b111 F
b110 F
b101 F
b100 F
b11 F
b10 F
b1 F
b0 F
b1111111000 E
b1111110000 E
#160000
0$
0-
1&
b10000000000001 '
b10 (
1/
1?
12
0B
#165000
1$
1-
b1001 F
b1000 F
b111 F
b110 F
b101 F
b100 F
b11 F
b10 F
b1 F
b0 F
b1111100000 E
b1111100001 E
#170000
0$
0-
b10000000000010 '
0?
1>
#175000
1$
1-
b1001 F
b1000 F
b111 F
b110 F
b101 F
b100 F
b11 F
b10 F
b1 F
b0 F
b1111000001 E
b1111000011 E
1C
b10000000000001 D
b10000000000001 *
1)
#180000
0$
0-
b10000000000011 '
1?
#185000
1$
1-
b1001 F
b1000 F
b111 F
b110 F
b101 F
b100 F
b11 F
b10 F
b1 F
b0 F
b1110000011 E
b1110000111 E
0C
b0 D
1C
b10000000000010 D
b10000000000010 *
#190000
0$
0-
b10000000000100 '
0?
0>
1=
#195000
1$
1-
b1001 F
b1000 F
b111 F
b110 F
b101 F
b100 F
b11 F
b10 F
b1 F
b0 F
b1100000111 E
b1100001111 E
0C
b0 D
1C
b10000000000011 D
b10000000000011 *
#200000
0$
0-
b11000000000001 '
b101 (
1?
0=
13
1B
0A
1@
0C
b0 D
b0 *
0)
#205000
1$
1-
b1001 F
b1000 F
b111 F
b110 F
b101 F
b100 F
b11 F
b10 F
b1 F
b0 F
b1000001111 E
b1000011111 E
1C
b10000000000001 D
b10000000000001 *
1)
#210000
0$
0-
b11000000000010 '
0?
1>
#215000
1$
1-
b1001 F
b1000 F
b111 F
b110 F
b101 F
b100 F
b11 F
b10 F
b1 F
b0 F
b11111 E
b111111 E
0C
b0 D
1C
b10000000000010 D
b10000000000010 *
#220000
0$
0-
b11000000000011 '
1?
#225000
1$
1-
b1001 F
b1000 F
b111 F
b110 F
b101 F
b100 F
b11 F
b10 F
b1 F
b0 F
b1111111 E
0C
b0 D
1C
b10000000000011 D
b10000000000011 *
#230000
0$
0-
b11000000000100 '
0?
0>
1=
#235000
1$
1-
b1001 F
b1000 F
b111 F
b110 F
b101 F
b100 F
b11 F
b10 F
b1 F
b0 F
b11111111 E
0C
b0 D
1C
b10000000000100 D
b10000000000100 *
#240000
0$
0-
0&
b0 '
0/
0=
03
02
#245000
1$
1-
b1001 F
b1000 F
b111 F
b110 F
b101 F
b100 F
b11 F
b10 F
b1 F
b0 F
b111111111 E
b111111110 E
0C
b0 D
1C
b11000000000001 D
b11000000000001 *
#250000
0$
0-
#255000
1$
1-
b1001 F
b1000 F
b111 F
b110 F
b101 F
b100 F
b11 F
b10 F
b1 F
b0 F
b1111111110 E
b1111111100 E
0C
b0 D
1C
b11000000000010 D
b11000000000010 *
#260000
0$
0-
#265000
1$
1-
b1001 F
b1000 F
b111 F
b110 F
b101 F
b100 F
b11 F
b10 F
b1 F
b0 F
b1111111000 E
0C
b0 D
1C
b11000000000011 D
b11000000000011 *
#270000
0$
0-
#275000
1$
1-
b1001 F
b1000 F
b111 F
b110 F
b101 F
b100 F
b11 F
b10 F
b1 F
b0 F
b1111110000 E
0C
b0 D
1C
b11000000000100 D
b11000000000100 *
#280000
0$
0-
#285000
1$
1-
b1001 F
b1000 F
b111 F
b110 F
b101 F
b100 F
b11 F
b10 F
b1 F
b0 F
b1111100000 E
0C
b0 D
b0 *
0)
#290000
0$
0-
#295000
1$
1-
b1001 F
b1000 F
b111 F
b110 F
b101 F
b100 F
b11 F
b10 F
b1 F
b0 F
b1111000000 E
#300000
0$
0-
#305000
1$
1-
b1001 F
b1000 F
b111 F
b110 F
b101 F
b100 F
b11 F
b10 F
b1 F
b0 F
b1110000000 E
