02_circular_queue_ppa/rtl/circular_queue_delay_logic.sv
`timescale 1ns/1ps

// -----------------------------------------------------------------------------
// Circular Queue based programmable delay logic
// - iDelay = N: outputs the input/valid pair stored N clock edges earlier.
// - iDataEn gates the input slot.
// - oDataEn gates oData; invalid output slots are forced to zero.
// - The data memory is intentionally not reset. valid_mem is reset, so stale
//   memory contents can never be observed as valid data. This also allows the
//   storage array to map efficiently to FPGA memory resources.
// -----------------------------------------------------------------------------
module circular_queue_delay_logic #(
    parameter int DATA_WIDTH  = 16,
    parameter int DEPTH       = 10,
    parameter int PTR_WIDTH   = (DEPTH <= 2) ? 1 : $clog2(DEPTH),
    parameter int DELAY_WIDTH = (DEPTH <= 1) ? 1 : $clog2(DEPTH + 1)
)(
    input  logic                   iClk,
    input  logic                   iRsn,
    input  logic                   iDataEn,
    input  logic [DATA_WIDTH-1:0]  iData,
    input  logic [DELAY_WIDTH-1:0] iDelay,
    output logic                   oDataEn,
    output logic [DATA_WIDTH-1:0]  oData
);

    // The queue stores one data word and one valid bit per clock slot.
    // Quartus may infer distributed memory/MLAB depending on DEPTH and device.
    logic [DATA_WIDTH-1:0] data_mem [0:DEPTH-1];
    logic [DEPTH-1:0]      valid_mem;

    logic [PTR_WIDTH-1:0] write_ptr;
    logic [PTR_WIDTH-1:0] read_ptr;
    logic                 delay_is_valid;

    integer read_index_int;

    // Read address = current write pointer - iDelay (mod DEPTH).
    // write_ptr points to the slot that will receive the next input word.
    always_comb begin
        read_index_int = 0;
        read_ptr       = '0;
        delay_is_valid = 1'b0;

        if ((iDelay >= 1) && (iDelay <= DEPTH)) begin
            delay_is_valid = 1'b1;
            if (write_ptr >= iDelay) begin
                read_index_int = write_ptr - iDelay;
            end else begin
                read_index_int = write_ptr + DEPTH - iDelay;
            end
            read_ptr = read_index_int[PTR_WIDTH-1:0];
        end
    end

    // Circular write operation: only one queue entry is updated each clock.
    always_ff @(posedge iClk or negedge iRsn) begin
        if (!iRsn) begin
            write_ptr <= '0;
            valid_mem <= '0;
        end else begin
            data_mem[write_ptr]  <= iDataEn ? iData : '0;
            valid_mem[write_ptr] <= iDataEn;

            if (write_ptr == DEPTH-1) begin
                write_ptr <= '0;
            end else begin
                write_ptr <= write_ptr + 1'b1;
            end
        end
    end

    // Output gating: invalid queue slots never propagate stale data.
    always_comb begin
        oDataEn = 1'b0;
        oData   = '0;

        if (iRsn && delay_is_valid) begin
            oDataEn = valid_mem[read_ptr];
            oData   = valid_mem[read_ptr] ? data_mem[read_ptr] : '0;
        end
    end

endmodule

02_circular_queue_ppa/tb/tb_circular_queue_delay_logic.sv
`timescale 1ns/1ps

module tb_circular_queue_delay_logic;

    localparam int DATA_WIDTH  = 16;
    localparam int DEPTH       = 10;
    localparam int DELAY_WIDTH = 4;
    localparam time CLK_PERIOD = 10ns;

    logic                   iClk;
    logic                   iRsn;
    logic                   iDataEn;
    logic [DATA_WIDTH-1:0]  iData;
    logic [DELAY_WIDTH-1:0] iDelay;
    logic                   oDataEn;
    logic [DATA_WIDTH-1:0]  oData;

    circular_queue_delay_logic #(
        .DATA_WIDTH(DATA_WIDTH),
        .DEPTH(DEPTH),
        .PTR_WIDTH(4),
        .DELAY_WIDTH(DELAY_WIDTH)
    ) dut (
        .iClk(iClk),
        .iRsn(iRsn),
        .iDataEn(iDataEn),
        .iData(iData),
        .iDelay(iDelay),
        .oDataEn(oDataEn),
        .oData(oData)
    );

    initial iClk = 1'b0;
    always #(CLK_PERIOD/2) iClk = ~iClk;

    task automatic drive_cycle(
        input logic                  en,
        input logic [DATA_WIDTH-1:0] data,
        input logic [DELAY_WIDTH-1:0] delay_value
    );
        begin
            @(negedge iClk);
            iDataEn = en;
            iData   = data;
            iDelay  = delay_value;
        end
    endtask

    initial begin
        iRsn    = 1'b0;
        iDataEn = 1'b0;
        iData   = '0;
        iDelay  = 4'd3;

        // Scenario 1: reset asserted and then released
        repeat (3) @(negedge iClk);
        iRsn = 1'b1;
        drive_cycle(1'b0, 16'h0000, 4'd3);
        drive_cycle(1'b0, 16'h0000, 4'd3);

        // Scenario 2: continuous Enable input, fixed iDelay=3
        drive_cycle(1'b1, 16'h1001, 4'd3);
        drive_cycle(1'b1, 16'h1002, 4'd3);
        drive_cycle(1'b1, 16'h1003, 4'd3);
        drive_cycle(1'b1, 16'h1004, 4'd3);
        drive_cycle(1'b1, 16'h1005, 4'd3);
        drive_cycle(1'b1, 16'h1006, 4'd3);
        drive_cycle(1'b0, 16'h0000, 4'd3);
        drive_cycle(1'b0, 16'h0000, 4'd3);
        drive_cycle(1'b0, 16'h0000, 4'd3);
        drive_cycle(1'b0, 16'h0000, 4'd3);

        // Scenario 3: change delay during operation (iDelay=2 -> 5)
        drive_cycle(1'b1, 16'h2001, 4'd2);
        drive_cycle(1'b1, 16'h2002, 4'd2);
        drive_cycle(1'b1, 16'h2003, 4'd2);
        drive_cycle(1'b1, 16'h2004, 4'd2);
        drive_cycle(1'b1, 16'h3001, 4'd5);
        drive_cycle(1'b1, 16'h3002, 4'd5);
        drive_cycle(1'b1, 16'h3003, 4'd5);
        drive_cycle(1'b1, 16'h3004, 4'd5);
        repeat (7) drive_cycle(1'b0, 16'h0000, 4'd5);

        #20;
        $finish;
    end

endmodule

results/archive_rerun/project2_original.vcd
$date
	Wed Jul 29 22:58:53 2026
$end
$version
	ModelSim Version 10.5b
$end
$timescale
	1ps
$end

$scope module tb_circular_queue_delay_logic $end
$var parameter 32 ! DATA_WIDTH $end
$var parameter 32 " DEPTH $end
$var parameter 32 # DELAY_WIDTH $end
$var parameter 64 $ CLK_PERIOD $end
$var reg 1 % iClk $end
$var reg 1 & iRsn $end
$var reg 1 ' iDataEn $end
$var reg 16 ( iData [15:0] $end
$var reg 4 ) iDelay [3:0] $end
$var reg 1 * oDataEn $end
$var reg 16 + oData [15:0] $end

$scope module dut $end
$var parameter 32 , DATA_WIDTH $end
$var parameter 32 - DEPTH $end
$var parameter 32 . PTR_WIDTH $end
$var parameter 32 / DELAY_WIDTH $end
$var wire 1 0 iClk $end
$var wire 1 1 iRsn $end
$var wire 1 2 iDataEn $end
$var wire 1 3 iData [15] $end
$var wire 1 4 iData [14] $end
$var wire 1 5 iData [13] $end
$var wire 1 6 iData [12] $end
$var wire 1 7 iData [11] $end
$var wire 1 8 iData [10] $end
$var wire 1 9 iData [9] $end
$var wire 1 : iData [8] $end
$var wire 1 ; iData [7] $end
$var wire 1 < iData [6] $end
$var wire 1 = iData [5] $end
$var wire 1 > iData [4] $end
$var wire 1 ? iData [3] $end
$var wire 1 @ iData [2] $end
$var wire 1 A iData [1] $end
$var wire 1 B iData [0] $end
$var wire 1 C iDelay [3] $end
$var wire 1 D iDelay [2] $end
$var wire 1 E iDelay [1] $end
$var wire 1 F iDelay [0] $end
$var reg 1 G oDataEn $end
$var reg 16 H oData [15:0] $end
$var reg 10 I valid_mem [9:0] $end
$var reg 4 J write_ptr [3:0] $end
$var reg 4 K read_ptr [3:0] $end
$var reg 1 L delay_is_valid $end
$var integer 32 M read_index_int $end
$upscope $end
$upscope $end
$enddefinitions $end
#0
$dumpvars
0%
0&
0'
b0 (
b11 )
0*
b0 +
0G
b0 H
b0 I
b0 J
b111 K
1L
b10000 !
b1010 "
b100 #
b1010 $
b10000 ,
b1010 -
b100 .
b100 /
b111 M
00
01
02
0B
0A
0@
0?
0>
0=
0<
0;
0:
09
08
07
06
05
04
03
1F
1E
0D
0C
$end
#5000
1%
10
#10000
0%
00
#15000
1%
10
#20000
0%
00
#25000
1%
10
#30000
0%
00
1&
11
#35000
1%
10
b1 J
b0 M
b0 K
0L
1L
b1000 M
b1000 K
#40000
0%
00
#45000
1%
10
b10 J
b0 M
b0 K
0L
1L
b1001 M
b1001 K
#50000
0%
00
#55000
1%
10
b11 J
b0 M
b0 K
0L
1L
#60000
0%
00
1'
b1000000000001 (
12
1B
16
#65000
1%
10
b1000 I
b100 J
0L
1L
b1 M
b1 K
#70000
0%
00
b1000000000010 (
0B
1A
#75000
1%
10
b11000 I
b101 J
b0 M
b0 K
0L
1L
b10 M
b10 K
#80000
0%
00
b1000000000011 (
1B
#85000
1%
10
b111000 I
b110 J
b0 M
b0 K
0L
1L
b11 M
b11 K
1G
b1000000000001 H
b1000000000001 +
1*
#90000
0%
00
b1000000000100 (
0B
0A
1@
#95000
1%
10
b1111000 I
b111 J
b0 M
b0 K
0L
1L
b100 M
b100 K
0G
b0 H
1G
b1000000000010 H
b1000000000010 +
#100000
0%
00
b1000000000101 (
1B
#105000
1%
10
b11111000 I
b1000 J
b0 M
b0 K
0L
1L
b101 M
b101 K
0G
b0 H
1G
b1000000000011 H
b1000000000011 +
#110000
0%
00
b1000000000110 (
0B
1A
#115000
1%
10
b111111000 I
b1001 J
b0 M
b0 K
0L
1L
b110 M
b110 K
0G
b0 H
1G
b1000000000100 H
b1000000000100 +
#120000
0%
00
0'
b0 (
02
0A
0@
06
#125000
1%
10
b0 J
b0 M
b0 K
0L
1L
b111 M
b111 K
0G
b0 H
1G
b1000000000101 H
b1000000000101 +
#130000
0%
00
#135000
1%
10
b1 J
b0 M
b0 K
0L
1L
b1000 M
b1000 K
0G
b0 H
1G
b1000000000110 H
b1000000000110 +
#140000
0%
00
#145000
1%
10
b10 J
b0 M
b0 K
0L
1L
b1001 M
b1001 K
0G
b0 H
b0 +
0*
#150000
0%
00
#155000
1%
10
b11 J
b0 M
b0 K
0L
1L
#160000
0%
00
1'
b10000000000001 (
b10 )
12
1B
15
0F
0L
1L
b1 M
b1 K
#165000
1%
10
b100 J
b0 M
b0 K
0L
1L
b10 M
b10 K
#170000
0%
00
b10000000000010 (
0B
1A
#175000
1%
10
b101 J
b0 M
b0 K
0L
1L
b11 M
b11 K
1G
b10000000000001 H
b10000000000001 +
1*
#180000
0%
00
b10000000000011 (
1B
#185000
1%
10
b110 J
b0 M
b0 K
0L
1L
b100 M
b100 K
0G
b0 H
1G
b10000000000010 H
b10000000000010 +
#190000
0%
00
b10000000000100 (
0B
0A
1@
#195000
1%
10
b111 J
b0 M
b0 K
0L
1L
b101 M
b101 K
0G
b0 H
1G
b10000000000011 H
b10000000000011 +
#200000
0%
00
b11000000000001 (
b101 )
1B
0@
16
1F
0E
1D
b0 M
b0 K
0L
1L
b10 M
b10 K
0G
b0 H
b0 +
0*
#205000
1%
10
b1000 J
b0 M
b0 K
0L
1L
b11 M
b11 K
1G
b10000000000001 H
b10000000000001 +
1*
#210000
0%
00
b11000000000010 (
0B
1A
#215000
1%
10
b1001 J
b0 M
b0 K
0L
1L
b100 M
b100 K
0G
b0 H
1G
b10000000000010 H
b10000000000010 +
#220000
0%
00
b11000000000011 (
1B
#225000
1%
10
b1111111000 I
b0 J
b0 M
b0 K
0L
1L
b101 M
b101 K
0G
b0 H
1G
b10000000000011 H
b10000000000011 +
#230000
0%
00
b11000000000100 (
0B
0A
1@
#235000
1%
10
b1111111001 I
b1 J
b0 M
b0 K
0L
1L
b110 M
b110 K
0G
b0 H
1G
b10000000000100 H
b10000000000100 +
#240000
0%
00
0'
b0 (
02
0@
06
05
#245000
1%
10
b10 J
b0 M
b0 K
0L
1L
b111 M
b111 K
0G
b0 H
1G
b11000000000001 H
b11000000000001 +
#250000
0%
00
#255000
1%
10
b11 J
b0 M
b0 K
0L
1L
b1000 M
b1000 K
0G
b0 H
1G
b11000000000010 H
b11000000000010 +
#260000
0%
00
#265000
1%
10
b1111110001 I
b100 J
b0 M
b0 K
0L
1L
b1001 M
b1001 K
0G
b0 H
1G
b11000000000011 H
b11000000000011 +
#270000
0%
00
#275000
1%
10
b1111100001 I
b101 J
b0 M
b0 K
0L
1L
0G
b0 H
1G
b11000000000100 H
b11000000000100 +
#280000
0%
00
#285000
1%
10
b1111000001 I
b110 J
0L
1L
b1 M
b1 K
0G
b0 H
b0 +
0*
#290000
0%
00
#295000
1%
10
b1110000001 I
b111 J
b0 M
b0 K
0L
1L
b10 M
b10 K
#300000
0%
00
#305000
1%
10
b1100000001 I
b1000 J
b0 M
b0 K
0L
1L
b11 M
b11 K
#310000
0%
00
#315000
1%
10
b1000000001 I
b1001 J
b0 M
b0 K
0L
1L
b100 M
b100 K
