01_shift_register_baseline/rtl/delay_logic.sv
`timescale 1ns/1ps

module delay_logic #(
    parameter int DATA_WIDTH = 16,
    parameter int DEPTH      = 10
)(
    input  logic                  iClk,
    input  logic                  iRsn,
    input  logic                  iDataEn,
    input  logic [DATA_WIDTH-1:0] iData,
    input  logic [2:0]            iDelay,
    output logic                  oDataEn,
    output logic [DATA_WIDTH-1:0] oData
);

    logic [DATA_WIDTH-1:0] data_shift [0:DEPTH-1];
    logic [DEPTH-1:0]      enable_shift;
    integer stage;

    // Shift-register datapath and enable pipeline
    always_ff @(posedge iClk or negedge iRsn) begin
        if (!iRsn) begin
            enable_shift <= '0;
            for (stage = 0; stage < DEPTH; stage = stage + 1) begin
                data_shift[stage] <= '0;
            end
        end else begin
            for (stage = DEPTH-1; stage > 0; stage = stage - 1) begin
                data_shift[stage]  <= data_shift[stage-1];
                enable_shift[stage] <= enable_shift[stage-1];
            end

            // Input gating by iDataEn
            data_shift[0]  <= iDataEn ? iData : '0;
            enable_shift[0] <= iDataEn;
        end
    end

    // Select the delayed tap. The lecture material defines iDelay as [2:0].
    // iDelay=0 is not used by the supplied verification scenarios.
    always_comb begin
        oDataEn = 1'b0;
        oData   = '0;

        if (iRsn && (iDelay != 3'd0)) begin
            oDataEn = enable_shift[iDelay-1];
            oData   = enable_shift[iDelay-1] ? data_shift[iDelay-1] : '0;
        end
    end

endmodule

01_shift_register_baseline/tb/tb_delay_logic_regression.sv
`timescale 1ns/1ps

// Portable, self-checking regression for the supplied Project 1 RTL.
// The reference pipeline below is intentionally independent of the DUT state.
module tb_delay_logic_regression;
    localparam integer DATA_WIDTH = 16;
    localparam integer DEPTH = 10;
    localparam time CLK_PERIOD = 10ns;

    logic iClk = 1'b0;
    logic iRsn = 1'b0;
    logic iDataEn = 1'b0;
    logic [DATA_WIDTH-1:0] iData = '0;
    logic [2:0] iDelay = 3'd3;
    logic oDataEn;
    logic [DATA_WIDTH-1:0] oData;

    logic [DATA_WIDTH-1:0] reference_data [0:DEPTH-1];
    logic [DEPTH-1:0] reference_valid;
    integer checks = 0;
    integer errors = 0;
    integer stage;

    delay_logic #(
        .DATA_WIDTH(DATA_WIDTH),
        .DEPTH(DEPTH)
    ) dut (
        .iClk(iClk),
        .iRsn(iRsn),
        .iDataEn(iDataEn),
        .iData(iData),
        .iDelay(iDelay),
        .oDataEn(oDataEn),
        .oData(oData)
    );

    always #(CLK_PERIOD/2) iClk = ~iClk;

    task automatic drive(
        input logic en,
        input logic [DATA_WIDTH-1:0] data,
        input logic [2:0] delay_value
    );
        begin
            @(negedge iClk);
            iDataEn = en;
            iData = data;
            iDelay = delay_value;
        end
    endtask

    always @(posedge iClk) begin
        if (!iRsn) begin
            reference_valid = '0;
            for (stage = 0; stage < DEPTH; stage = stage + 1)
                reference_data[stage] = '0;
        end
        else begin
            for (stage = DEPTH-1; stage > 0; stage = stage - 1) begin
                reference_data[stage] = reference_data[stage-1];
                reference_valid[stage] = reference_valid[stage-1];
            end
            reference_data[0] = iDataEn ? iData : '0;
            reference_valid[0] = iDataEn;
        end

        #1;
        if (iRsn) begin
            checks = checks + 1;
            if ((iDelay == 0) ||
                (oDataEn !== reference_valid[iDelay-1]) ||
                (oData !== (reference_valid[iDelay-1] ?
                            reference_data[iDelay-1] : '0))) begin
                errors = errors + 1;
                $display(
                    "[P1][ERROR] check=%0d delay=%0d en=%0b data=%04h expected_en=%0b expected_data=%04h",
                    checks, iDelay, oDataEn, oData,
                    (iDelay == 0) ? 1'b0 : reference_valid[iDelay-1],
                    (iDelay == 0) ? 16'h0000 :
                        (reference_valid[iDelay-1] ? reference_data[iDelay-1] : '0)
                );
            end
        end
    end

    initial begin
        $dumpfile("results/project1_waveform.vcd");
        $dumpvars(0, tb_delay_logic_regression);

        repeat (3) @(negedge iClk);
        iRsn = 1'b1;

        // Fixed delay with continuous data.
        drive(1'b1, 16'h1001, 3'd3);
        drive(1'b1, 16'h1002, 3'd3);
        drive(1'b1, 16'h1003, 3'd3);
        drive(1'b1, 16'h1004, 3'd3);

        // Sparse valid traffic.
        drive(1'b0, 16'hDEAD, 3'd3);
        drive(1'b1, 16'h2001, 3'd3);
        drive(1'b0, 16'hBEEF, 3'd3);
        drive(1'b1, 16'h2002, 3'd3);

        // Runtime tap changes.
        drive(1'b1, 16'h3001, 3'd2);
        drive(1'b1, 16'h3002, 3'd2);
        drive(1'b1, 16'h4001, 3'd5);
        drive(1'b0, 16'h0000, 3'd5);
        repeat (7) drive(1'b0, 16'h0000, 3'd5);

        @(posedge iClk);
        #2;
        if (errors == 0)
            $display("[P1][PASS] checks=%0d errors=0", checks);
        else
            $display("[P1][FAIL] checks=%0d errors=%0d", checks, errors);
        $finish_and_return(errors == 0 ? 0 : 1);
    end
endmodule

01_shift_register_baseline/results/project1_waveform.vcd
$date
	Wed Jul 29 22:59:32 2026
$end
$version
	Icarus Verilog
$end
$timescale
	1ps
$end
$scope module tb_delay_logic_regression $end
$var wire 1 ! oDataEn $end
$var wire 16 " oData [15:0] $end
$var parameter 64 # CLK_PERIOD $end
$var parameter 32 $ DATA_WIDTH $end
$var parameter 32 % DEPTH $end
$var reg 1 & iClk $end
$var reg 16 ' iData [15:0] $end
$var reg 1 ( iDataEn $end
$var reg 3 ) iDelay [2:0] $end
$var reg 1 * iRsn $end
$var reg 10 + reference_valid [9:0] $end
$var integer 32 , checks [31:0] $end
$var integer 32 - errors [31:0] $end
$var integer 32 . stage [31:0] $end
$scope module dut $end
$var wire 1 & iClk $end
$var wire 16 / iData [15:0] $end
$var wire 1 ( iDataEn $end
$var wire 3 0 iDelay [2:0] $end
$var wire 1 * iRsn $end
$var parameter 32 1 DATA_WIDTH $end
$var parameter 32 2 DEPTH $end
$var reg 10 3 enable_shift [9:0] $end
$var reg 16 4 oData [15:0] $end
$var reg 1 ! oDataEn $end
$var integer 32 5 stage [31:0] $end
$upscope $end
$scope task drive $end
$upscope $end
$upscope $end
$enddefinitions $end
$comment Show the parameter values. $end
$dumpall
b1010 2
b10000 1
b1010 %
b10000 $
b1010 #
$end
#0
$dumpvars
bx 5
b0 4
bx 3
b11 0
b0 /
bx .
b0 -
b0 ,
bx +
0*
b11 )
0(
b0 '
0&
b0 "
0!
$end
#5000
b0 3
b1010 5
b1010 .
b0 +
1&
#10000
0&
#15000
b1010 5
b1010 .
1&
#20000
0&
#25000
b1010 5
b1010 .
1&
#30000
1*
0&
#35000
b0 5
b0 .
1&
#36000
b1 ,
#40000
b1000000000001 '
b1000000000001 /
1(
0&
#45000
b1 3
b0 5
b1 +
b0 .
1&
#46000
b10 ,
#50000
b1000000000010 '
b1000000000010 /
0&
#55000
b11 3
b0 5
b11 +
b0 .
1&
#56000
b11 ,
#60000
b1000000000011 '
b1000000000011 /
0&
#65000
b1000000000001 "
b1000000000001 4
1!
b111 3
b0 5
b111 +
b0 .
1&
#66000
b100 ,
#70000
b1000000000100 '
b1000000000100 /
0&
#75000
b1000000000010 "
b1000000000010 4
1!
b1111 3
b0 5
b1111 +
b0 .
1&
#76000
b101 ,
#80000
b1101111010101101 '
b1101111010101101 /
0(
0&
#85000
b1000000000011 "
b1000000000011 4
1!
b11110 3
b0 5
b11110 +
b0 .
1&
#86000
b110 ,
#90000
b10000000000001 '
b10000000000001 /
1(
0&
#95000
b1000000000100 "
b1000000000100 4
1!
b111101 3
b0 5
b111101 +
b0 .
1&
#96000
b111 ,
#100000
b1011111011101111 '
b1011111011101111 /
0(
0&
#105000
b0 "
b0 4
0!
b1111010 3
b0 5
b1111010 +
b0 .
1&
#106000
b1000 ,
#110000
b10000000000010 '
b10000000000010 /
1(
0&
#115000
b10000000000001 "
b10000000000001 4
1!
b11110101 3
b0 5
b11110101 +
b0 .
1&
#116000
b1001 ,
#120000
b0 "
b0 4
0!
b10 )
b10 0
b11000000000001 '
b11000000000001 /
0&
#125000
b10000000000010 "
b10000000000010 4
1!
b111101011 3
b0 5
b111101011 +
b0 .
1&
#126000
b1010 ,
#130000
b11000000000010 '
b11000000000010 /
0&
#135000
b11000000000001 "
b11000000000001 4
1!
b1111010111 3
b0 5
b1111010111 +
b0 .
1&
#136000
b1011 ,
#140000
b10000000000001 "
b10000000000001 4
1!
b101 )
b101 0
b100000000000001 '
b100000000000001 /
0&
#145000
b0 "
b0 4
0!
b1110101111 3
b0 5
b1110101111 +
b0 .
1&
#146000
b1100 ,
#150000
b0 '
b0 /
0(
0&
#155000
b10000000000010 "
b10000000000010 4
1!
b1101011110 3
b0 5
b1101011110 +
b0 .
1&
#156000
b1101 ,
#160000
0&
#165000
b11000000000001 "
b11000000000001 4
1!
b1010111100 3
b0 5
b1010111100 +
b0 .
1&
#166000
b1110 ,
#170000
0&
#175000
b11000000000010 "
b11000000000010 4
1!
b101111000 3
b0 5
b101111000 +
b0 .
1&
#176000
b1111 ,
#180000
0&
#185000
b100000000000001 "
b100000000000001 4
1!
b1011110000 3
b0 5
b1011110000 +
b0 .
1&
#186000
b10000 ,
#190000
0&
#195000
b0 "
b0 4
0!
b111100000 3
b0 5
b111100000 +
b0 .
1&
#196000
b10001 ,
#200000
0&
#205000
b1111000000 3
b0 5
b1111000000 +
b0 .
1&
#206000
b10010 ,
#210000
0&
#215000
b1110000000 3
b0 5
b1110000000 +
b0 .
1&
#216000
b10011 ,
#220000
0&
#225000
b1100000000 3
b0 5
b1100000000 +
b0 .
1&
#226000
b10100 ,
